CHANGES.txt
README.txt
buildout.cfg
demo.ini
ez_setup.py
setup.cfg
setup.py
src/repoze/__init__.py
src/repoze.filecat.egg-info/PKG-INFO
src/repoze.filecat.egg-info/SOURCES.txt
src/repoze.filecat.egg-info/dependency_links.txt
src/repoze.filecat.egg-info/entry_points.txt
src/repoze.filecat.egg-info/namespace_packages.txt
src/repoze.filecat.egg-info/not-zip-safe
src/repoze.filecat.egg-info/requires.txt
src/repoze.filecat.egg-info/top_level.txt
src/repoze/filecat/__init__.py
src/repoze/filecat/configure.zcml
src/repoze/filecat/extraction.py
src/repoze/filecat/index.py
src/repoze/filecat/interfaces.py
src/repoze/filecat/jpeg.py
src/repoze/filecat/json.py
src/repoze/filecat/resolver.py
src/repoze/filecat/resource.py
src/repoze/filecat/run.py
src/repoze/filecat/views.py
src/repoze/filecat/watch.py
src/repoze/filecat/xapian.py
src/repoze/filecat/xapian.zcml
src/repoze/filecat/tests/__init__.py
src/repoze/filecat/tests/test_filecat.py
src/repoze/filecat/tests/static/sample.jpg
src/repoze/filecat/tests/static/sample.rst