Metadata-Version: 1.0
Name: repoze.filecat
Version: 0.2
Summary: A file catalog with an HTTP frontend.
Home-page: http://www.repoze.org
Author: Malthe Borch and Stefan Eletzhofer
Author-email: repoze-dev@lists.repoze.org
License: BSD-derived (http://www.repoze.org/LICENSE.txt)
Keywords: web wsgi bfg zope
Platform: UNKNOWN
Classifier: Development Status :: 3 - Alpha
Classifier: Intended Audience :: Developers
Classifier: Programming Language :: Python
Classifier: Topic :: Internet :: WWW/HTTP
Classifier: Topic :: Internet :: WWW/HTTP :: WSGI
Classifier: Topic :: Internet :: WWW/HTTP :: WSGI :: Application
